quri_algo/algo/__init__.py
quri_algo/algo/compiler/__init__.py
quri_algo/algo/compiler/base_classes.py
quri_algo/algo/compiler/qaqc.py
quri_algo/algo/interface.py
quri_algo/algo/phase_estimation/__init__.py
quri_algo/algo/phase_estimation/interface.py
quri_algo/algo/phase_estimation/qpe/__init__.py
quri_algo/algo/phase_estimation/qpe/qpe.py
quri_algo/algo/phase_estimation/spe/__init__.py
quri_algo/algo/phase_estimation/spe/gaussian/__init__.py
quri_algo/algo/phase_estimation/spe/gaussian/fitting.py
quri_algo/algo/phase_estimation/spe/gaussian/param_choice.py
quri_algo/algo/phase_estimation/spe/interface.py
quri_algo/algo/phase_estimation/spe/lt22.py
quri_algo/algo/phase_estimation/spe/utils/__init__.py
quri_algo/algo/phase_estimation/spe/utils/exp_val_collector.py
quri_algo/algo/phase_estimation/spe/utils/fourier/__init__.py
quri_algo/algo/phase_estimation/spe/utils/fourier/coefficient.py
quri_algo/algo/phase_estimation/spe/utils/fourier/gaussian_coefficient.py
quri_algo/algo/phase_estimation/spe/utils/fourier/step_func_coefficient.py
quri_algo/algo/phase_estimation/spe/utils/recorder.py
quri_algo/algo/phase_estimation/spe/utils/signal.py
quri_algo/algo/py.typed
quri_algo/algo/utils/mappings.py
quri_algo/algo/utils/timer.py
quri_algo/algo/utils/variational_solvers.py
quri_algo/circuit/__init__.py
quri_algo/circuit/hadamard_test.py
quri_algo/circuit/interface.py
quri_algo/circuit/time_evolution/__init__.py
quri_algo/circuit/time_evolution/exact_unitary.py
quri_algo/circuit/time_evolution/interface.py
quri_algo/circuit/time_evolution/trotter_time_evo.py
quri_algo/circuit/utils/__init__.py
quri_algo/circuit/utils/transpile.py
quri_algo/core/__init__.py
quri_algo/core/cost_functions/__init__.py
quri_algo/core/cost_functions/base_classes.py
quri_algo/core/cost_functions/hilbert_schmidt_test.py
quri_algo/core/cost_functions/utils.py
quri_algo/core/estimator/__init__.py
quri_algo/core/estimator/hadamard_test.py
quri_algo/core/estimator/interface.py
quri_algo-0.24.1.dist-info/LICENSE
quri_algo-0.24.1.dist-info/METADATA
quri_algo-0.24.1.dist-info/WHEEL
quri_algo-0.24.1.dist-info/RECORD
