Metadata-Version: 2.1
Name: quri-algo
Version: 0.24.1
Summary: Algorithm library based on QURI Parts
Home-page: https://github.com/QunaSys/quri-algo
License: MIT
Keywords: quantum,quantum computing
Author: QunaSys
Requires-Python: >=3.10,<4
Classifier: License :: OSI Approved :: MIT License
Classifier: Programming Language :: Python :: 3
Classifier: Programming Language :: Python :: 3.10
Classifier: Programming Language :: Python :: 3.11
Classifier: Programming Language :: Python :: 3.12
Classifier: Programming Language :: Python :: 3.13
Classifier: Topic :: Scientific/Engineering :: Physics
Classifier: Typing :: Typed
Requires-Dist: pytest (>=8.3.3,<9.0.0)
Requires-Dist: quri-parts-algo
Requires-Dist: quri-parts-chem
Requires-Dist: quri-parts-circuit
Requires-Dist: quri-parts-core
Requires-Dist: quri-parts-openfermion
Requires-Dist: quri-parts-pyscf
Requires-Dist: quri-parts-qsub
Requires-Dist: quri-parts-qulacs
Requires-Dist: quri-parts-rust
Project-URL: Documentation, https://quri-sdk.qunasys.com
Project-URL: Repository, https://github.com/QunaSys/quri-algo
